{
    "time":60,
    "tasks": [
        {
            "tag":"phatam",
            "thematics":[
                {
                    "tag":"duoied",
                    "detail":[
                        {
                            "difficulty":1000,
                            "number":1
                        }
                    ]
                    
                },
                {
                    "tag":"nguyenamphuam",
                    "detail":[
                        {
                            "difficulty":1000,
                            "number":1
                        }
                    ]
                    
                }
            ]
        },
        {
            "tag":"trongam",
            "thematics":[
                {
                    "tag":"2amtiet",
                    "detail":[
                        {
                            "difficulty":1000,
                            "number":1  
                        }
                    ]
                    
                },
                {
                    "tag":"nhieuamtiet",
                    "detail":[
                        {
                            "difficulty":1000,
                            "number":1
                        }
                    ]
                }
            ]
        },
        {
            "tag":"chondapandung",
            "thematics":[
                {
                    "tag":"cauhoiduoi",
                    "detail":[
                        {
                            "difficulty":1000,
                            "number":1
                        }
                    ]
                },
                {
                    "tag":"gioitu",
                    "detail":[
                        {
                            "difficulty":1000,
                            "number":1
                        }
                    ]
                },
                {
                    "tag":"sosanhkep",
                    "detail":[
                        {
                            "difficulty":1000,
                            "number":1
                        }
                    ]
                },
                {
                    "tag":"caubidong",
                    "detail":[
                        {
                            "difficulty":1000,
                            "number":1
                        }
                    ]
                },
                {
                    "tag":"trattutinhtu",
                    "detail":[
                        {
                            "difficulty":2000,
                            "number":1
                        }
                    ]
                },
                {
                    "tag":"qktd",
                    "detail":[
                        {
                            "difficulty":1000,
                            "number":1
                        }
                    ]
                },
                {
                    "tag":"lientu",
                    "detail":[
                        {
                            "difficulty":2000,
                            "number":1
                        }
                    ]
                },
                {
                    "tag":"phoihopthi",
                    "detail":[
                        {
                            "difficulty":2000,
                            "number":1
                        }
                    ]
                },
                {
                    "tag":"mdtn",
                    "detail":[
                        {
                            "difficulty":3000,
                            "number":1
                        }
                    ]
                },
                {
                    "tag":"tuloai",
                    "detail":[
                        {
                            "difficulty":1000,
                            "number":1
                        }
                    ]
                },
                {
                    "tag":"cumdongtu",
                    "detail":[
                        {
                            "difficulty":3000,
                            "number":1
                        }
                    ]
                },
                {
                    "tag":"cumtucodinh",
                    "detail":[
                        {
                            "difficulty":3000,
                            "number":1
                        }
                    ]
                },
                {
                    "tag":"thanhngu",
                    "detail":[
                        {
                            "difficulty":4000,
                            "number":1
                        }
                    ]
                },
                {
                    "tag":"tuvung1",
                    "detail":[
                        {
                            "difficulty":3000,
                            "number":1
                        },
                        {
                            "difficulty":4000,
                            "number":1
                        }
                    ]
                }
            ]
        },
        {
            "tag":"dongnghia",
            "thematics":[
                {
                    "tag":"tudon1",
                    "detail":[
                        {
                            "difficulty":2000,
                            "number":1  
                        },
                        {
                            "difficulty":3000,
                            "number":1  
                        }
                    ]
                    
                }
            ]
        },
        {
            "tag":"trainghia",
            "thematics":[
                {
                    "tag":"tudon2",
                    "detail":[
                        {
                            "difficulty":2000,
                            "number":1  
                        }
                    ]
                },
                {
                    "tag":"cumtuthanhngu",
                    "detail":[
                        {
                            "difficulty":4000,
                            "number":1  
                        }
                    ]
                }
            ]
        },
        {
            "tag":"giaotiep",
            "thematics":[
                {
                    "tag":"thgt",
                    "detail":[
                        {
                            "difficulty":1000,
                            "number":2  
                        }
                    ]
                }
            ]
        },
        {
            "tag":"docdientu",
            "thematics":[
                {
                    "tag":"lientutrangtulk",
                    "detail":[
                        {
                            "difficulty":2000,
                            "number":1
                        }
                    ]
                },
                {
                    "tag":"dtqh",
                    "detail":[
                        {
                            "difficulty":1000,
                            "number":1
                        }
                    ]
                },
                {
                    "tag":"tuvung2",
                    "detail":[
                        {
                            "difficulty":3000,
                            "number":1
                        },
                        {
                            "difficulty":4000,
                            "number":1
                        }
                    ]
                },
                {
                    "tag":"luongtu",
                    "detail":[
                        {
                            "difficulty":2000,
                            "number":1
                        }
                    ]
                }
            ]
        },
        {
            "tag":"dochieudoanvan",
            "thematics":[
                {
                    "tag":"mainidea",
                    "detail":[
                        {
                            "difficulty":2000,
                            "number":1
                        }
                    ]
                },
                {
                    "tag":"truenotrue",
                    "detail":[
                        {
                            "difficulty":1000,
                            "number":1
                        }
                    ]
                },
                {
                    "tag":"ttct",
                    "detail":[
                        {
                            "difficulty":2000,
                            "number":1
                        }
                    ]
                },
                {
                    "tag":"quychieu",
                    "detail":[
                        {
                            "difficulty":1000,
                            "number":1
                        }
                    ]
                },
                {
                    "tag":"tv",
                    "detail":[
                        {
                            "difficulty":2000,
                            "number":1
                        }
                    ]
                }
            ]
        },
        {
            "tag":"dochieudoanvan",
            "thematics":[
                {
                    "tag":"mainidea",
                    "detail":[
                        {
                            "difficulty":3000,
                            "number":1
                        }
                    ]
                },
                {
                    "tag":"truenotrue",
                    "detail":[
                        {
                            "difficulty":3000,
                            "number":1
                        }
                    ]
                },
                {
                    "tag":"ttct",
                    "detail":[
                        {
                            "difficulty":3000,
                            "number":1
                        }
                    ]
                },
                {
                    "tag":"quychieu",
                    "detail":[
                        {
                            "difficulty":2000,
                            "number":1
                        }
                    ]
                },
                {
                    "tag":"tv",
                    "detail":[
                        {
                            "difficulty":2000,
                            "number":1
                        },
                        {
                            "difficulty":3000,
                            "number":1
                        }
                    ]
                },
                {
                    "tag":"suyluan",
                    "detail":[
                        {
                            "difficulty":4000,
                            "number":1
                        }
                    ]
                }
            ]
        },
        {
            "tag":"timloisai",
            "thematics":[
                {
                    "tag":"thi",
                    "detail":[
                        {
                            "difficulty":1000,
                            "number":1
                        }
                    ]
                },
                {
                    "tag":"pqc",
                    "detail":[
                        {
                            "difficulty":2000,
                            "number":1
                        }
                    ]
                },
                {
                    "tag":"tuvung3",
                    "detail":[
                        {
                            "difficulty":4000,
                            "number":1
                        }
                    ]
                }
            ]
        },
        {
            "tag":"caudongnghia",
            "thematics":[
                {
                    "tag":"cdt",
                    "detail":[
                        {
                            "difficulty":2000,
                            "number":1
                        }
                    ]
                },
                {
                    "tag":"ctt",
                    "detail":[
                        {
                            "difficulty":2000,
                            "number":1
                        }
                    ]
                },
                {
                    "tag":"khuyetthieu",
                    "detail":[
                        {
                            "difficulty":2000,
                            "number":1
                        }
                    ]
                }
            ]
        },
        {
            "tag":"kethopcau",
            "thematics":[
                {
                    "tag":"cauuoccaudieukien",
                    "detail":[
                        {
                            "difficulty":3000,
                            "number":1
                        }
                    ]
                },
                {
                    "tag":"daongu",
                    "detail":[
                        {
                            "difficulty":3000,
                            "number":1
                        }
                    ]
                }
            ]
        }
    ]
}